{
  "datamodel": {
    "enums": [
      {
        "name": "Tree",
        "values": [
          "ARBORVITAE",
          "YELLOWBIRCH",
          "BLACKASH",
          "DOUGLASFIR",
          "OAK"
        ],
        "dbName": null
      },
      {
        "name": "Permission",
        "values": [
          "ADMIN",
          "USER",
          "OWNER",
          "COLLABORATOR"
        ],
        "dbName": null
      }
    ],
    "models": [
      {
        "name": "User",
        "isEmbedded": false,
        "dbName": null,
        "fields": [
          {
            "name": "id",
            "kind": "scalar",
            "dbName": null,
            "isList": false,
            "isRequired": true,
            "isUnique": false,
            "isId": true,
            "type": "Int",
            "isGenerated": false
          },
          {
            "name": "name",
            "kind": "scalar",
            "dbName": null,
            "isList": false,
            "isRequired": true,
            "isUnique": false,
            "isId": false,
            "type": "String",
            "isGenerated": false
          },
          {
            "name": "email",
            "kind": "scalar",
            "dbName": null,
            "isList": false,
            "isRequired": true,
            "isUnique": true,
            "isId": false,
            "type": "String",
            "isGenerated": false
          },
          {
            "name": "status",
            "kind": "scalar",
            "dbName": null,
            "isList": false,
            "isRequired": true,
            "isUnique": false,
            "isId": false,
            "type": "String",
            "isGenerated": false
          },
          {
            "name": "nicknames",
            "kind": "scalar",
            "dbName": null,
            "isList": true,
            "isRequired": false,
            "isUnique": false,
            "isId": false,
            "type": "String",
            "isGenerated": false
          },
          {
            "name": "permissions",
            "kind": "enum",
            "dbName": null,
            "isList": true,
            "isRequired": false,
            "isUnique": false,
            "isId": false,
            "type": "Permission",
            "isGenerated": false
          },
          {
            "name": "favoriteTree",
            "kind": "enum",
            "dbName": null,
            "isList": false,
            "isRequired": true,
            "isUnique": false,
            "isId": false,
            "type": "Tree",
            "isGenerated": false
          },
          {
            "name": "location",
            "kind": "object",
            "dbName": null,
            "isList": false,
            "isRequired": true,
            "isUnique": false,
            "isId": false,
            "type": "Location",
            "relationToFields": [],
            "relationOnDelete": "NONE",
            "isGenerated": false
          },
          {
            "name": "posts",
            "kind": "object",
            "dbName": null,
            "isList": true,
            "isRequired": false,
            "isUnique": false,
            "isId": false,
            "type": "Post",
            "relationToFields": [],
            "relationOnDelete": "NONE",
            "isGenerated": false
          }
        ]
      },
      {
        "name": "Post",
        "isEmbedded": false,
        "dbName": null,
        "fields": [
          {
            "name": "id",
            "kind": "scalar",
            "dbName": null,
            "isList": false,
            "isRequired": true,
            "isUnique": false,
            "isId": true,
            "type": "Int",
            "isGenerated": false
          },
          {
            "name": "name",
            "kind": "scalar",
            "dbName": null,
            "isList": false,
            "isRequired": true,
            "isUnique": false,
            "isId": false,
            "type": "String",
            "isGenerated": false
          },
          {
            "name": "email",
            "kind": "scalar",
            "dbName": null,
            "isList": false,
            "isRequired": true,
            "isUnique": true,
            "isId": false,
            "type": "String",
            "isGenerated": false
          },
          {
            "name": "user",
            "kind": "object",
            "dbName": null,
            "isList": false,
            "isRequired": false,
            "isUnique": false,
            "isId": false,
            "type": "User",
            "relationToFields": [],
            "relationOnDelete": "NONE",
            "isGenerated": true
          }
        ]
      },
      {
        "name": "Location",
        "isEmbedded": false,
        "dbName": null,
        "fields": [
          {
            "name": "id",
            "kind": "scalar",
            "dbName": null,
            "isList": false,
            "isRequired": true,
            "isUnique": false,
            "isId": true,
            "type": "Int",
            "isGenerated": false
          },
          {
            "name": "city",
            "kind": "scalar",
            "dbName": null,
            "isList": false,
            "isRequired": true,
            "isUnique": false,
            "isId": false,
            "type": "String",
            "isGenerated": false
          },
          {
            "name": "user",
            "kind": "object",
            "dbName": null,
            "isList": false,
            "isRequired": false,
            "isUnique": false,
            "isId": false,
            "type": "User",
            "relationToFields": [],
            "relationOnDelete": "NONE",
            "isGenerated": true
          }
        ]
      }
    ]
  },
  "mappings": [
    {
      "model": "User",
      "findOne": "user",
      "findMany": "users",
      "create": "createUser",
      "update": null,
      "updateMany": null,
      "upsert": null,
      "delete": null,
      "deleteMany": null
    },
    {
      "model": "Post",
      "findOne": "post",
      "findMany": "posts",
      "create": "createPost",
      "update": null,
      "updateMany": null,
      "upsert": null,
      "delete": null,
      "deleteMany": null
    },
    {
      "model": "Location",
      "findOne": "location",
      "findMany": "locations",
      "create": "createLocation",
      "update": null,
      "updateMany": null,
      "upsert": null,
      "delete": null,
      "deleteMany": null
    }
  ],
  "schema": {
    "enums": [
      {
        "name": "OrderByArg",
        "values": [
          "asc",
          "desc"
        ]
      },
      {
        "name": "Tree",
        "values": [
          "ARBORVITAE",
          "YELLOWBIRCH",
          "BLACKASH",
          "DOUGLASFIR",
          "OAK"
        ]
      },
      {
        "name": "Permission",
        "values": [
          "ADMIN",
          "USER",
          "OWNER",
          "COLLABORATOR"
        ]
      }
    ],
    "outputTypes": [
      {
        "name": "Location",
        "fields": [
          {
            "name": "id",
            "args": [],
            "outputType": {
              "type": "Int",
              "kind": "scalar",
              "isRequired": true,
              "isList": false
            }
          },
          {
            "name": "city",
            "args": [],
            "outputType": {
              "type": "String",
              "kind": "scalar",
              "isRequired": true,
              "isList": false
            }
          },
          {
            "name": "user",
            "args": [],
            "outputType": {
              "type": "User",
              "kind": "object",
              "isRequired": false,
              "isList": false
            }
          }
        ]
      },
      {
        "name": "Post",
        "fields": [
          {
            "name": "id",
            "args": [],
            "outputType": {
              "type": "Int",
              "kind": "scalar",
              "isRequired": true,
              "isList": false
            }
          },
          {
            "name": "name",
            "args": [],
            "outputType": {
              "type": "String",
              "kind": "scalar",
              "isRequired": true,
              "isList": false
            }
          },
          {
            "name": "email",
            "args": [],
            "outputType": {
              "type": "String",
              "kind": "scalar",
              "isRequired": true,
              "isList": false
            }
          },
          {
            "name": "user",
            "args": [],
            "outputType": {
              "type": "User",
              "kind": "object",
              "isRequired": false,
              "isList": false
            }
          }
        ]
      },
      {
        "name": "User",
        "fields": [
          {
            "name": "id",
            "args": [],
            "outputType": {
              "type": "Int",
              "kind": "scalar",
              "isRequired": true,
              "isList": false
            }
          },
          {
            "name": "name",
            "args": [],
            "outputType": {
              "type": "String",
              "kind": "scalar",
              "isRequired": true,
              "isList": false
            }
          },
          {
            "name": "email",
            "args": [],
            "outputType": {
              "type": "String",
              "kind": "scalar",
              "isRequired": true,
              "isList": false
            }
          },
          {
            "name": "status",
            "args": [],
            "outputType": {
              "type": "String",
              "kind": "scalar",
              "isRequired": true,
              "isList": false
            }
          },
          {
            "name": "nicknames",
            "args": [],
            "outputType": {
              "type": "String",
              "kind": "scalar",
              "isRequired": true,
              "isList": true
            }
          },
          {
            "name": "permissions",
            "args": [],
            "outputType": {
              "type": "Permission",
              "kind": "enum",
              "isRequired": true,
              "isList": true
            }
          },
          {
            "name": "favoriteTree",
            "args": [],
            "outputType": {
              "type": "Tree",
              "kind": "enum",
              "isRequired": true,
              "isList": false
            }
          },
          {
            "name": "location",
            "args": [],
            "outputType": {
              "type": "Location",
              "kind": "object",
              "isRequired": true,
              "isList": false
            }
          },
          {
            "name": "posts",
            "args": [
              {
                "name": "where",
                "inputType": [
                  {
                    "type": "UserWhereInput",
                    "kind": "object",
                    "isRequired": false,
                    "isList": false
                  }
                ]
              },
              {
                "name": "orderBy",
                "inputType": [
                  {
                    "type": "UserOrderByInput",
                    "kind": "enum",
                    "isRequired": false,
                    "isList": false
                  }
                ]
              },
              {
                "name": "skip",
                "inputType": [
                  {
                    "type": "String",
                    "kind": "scalar",
                    "isRequired": false,
                    "isList": false
                  }
                ]
              },
              {
                "name": "after",
                "inputType": [
                  {
                    "type": "String",
                    "kind": "scalar",
                    "isRequired": false,
                    "isList": false
                  }
                ]
              },
              {
                "name": "before",
                "inputType": [
                  {
                    "type": "String",
                    "kind": "scalar",
                    "isRequired": false,
                    "isList": false
                  }
                ]
              },
              {
                "name": "first",
                "inputType": [
                  {
                    "type": "Int",
                    "kind": "scalar",
                    "isRequired": false,
                    "isList": false
                  }
                ]
              },
              {
                "name": "last",
                "inputType": [
                  {
                    "type": "Int",
                    "kind": "scalar",
                    "isRequired": false,
                    "isList": false
                  }
                ]
              }
            ],
            "outputType": {
              "type": "Post",
              "kind": "object",
              "isRequired": false,
              "isList": true
            }
          }
        ]
      },
      {
        "name": "Query",
        "fields": [
          {
            "name": "users",
            "args": [
              {
                "name": "where",
                "inputType": [
                  {
                    "type": "UserWhereInput",
                    "kind": "object",
                    "isRequired": false,
                    "isList": false
                  }
                ]
              },
              {
                "name": "orderBy",
                "inputType": [
                  {
                    "type": "UserOrderByInput",
                    "kind": "enum",
                    "isRequired": false,
                    "isList": false
                  }
                ]
              },
              {
                "name": "skip",
                "inputType": [
                  {
                    "type": "String",
                    "kind": "scalar",
                    "isRequired": false,
                    "isList": false
                  }
                ]
              },
              {
                "name": "after",
                "inputType": [
                  {
                    "type": "String",
                    "kind": "scalar",
                    "isRequired": false,
                    "isList": false
                  }
                ]
              },
              {
                "name": "before",
                "inputType": [
                  {
                    "type": "String",
                    "kind": "scalar",
                    "isRequired": false,
                    "isList": false
                  }
                ]
              },
              {
                "name": "first",
                "inputType": [
                  {
                    "type": "Int",
                    "kind": "scalar",
                    "isRequired": false,
                    "isList": false
                  }
                ]
              },
              {
                "name": "last",
                "inputType": [
                  {
                    "type": "Int",
                    "kind": "scalar",
                    "isRequired": false,
                    "isList": false
                  }
                ]
              }
            ],
            "outputType": {
              "type": "User",
              "kind": "object",
              "isRequired": false,
              "isList": true
            }
          },
          {
            "name": "user",
            "args": [
              {
                "name": "where",
                "inputType": [
                  {
                    "type": "UserWhereUniqueInput",
                    "kind": "object",
                    "isRequired": true,
                    "isList": false
                  }
                ]
              }
            ],
            "outputType": {
              "type": "User",
              "kind": "object",
              "isRequired": false,
              "isList": false
            }
          },
          {
            "name": "posts",
            "args": [
              {
                "name": "where",
                "inputType": [
                  {
                    "type": "PostWhereInput",
                    "kind": "object",
                    "isRequired": false,
                    "isList": false
                  }
                ]
              },
              {
                "name": "orderBy",
                "inputType": [
                  {
                    "type": "PostOrderByInput",
                    "kind": "enum",
                    "isRequired": false,
                    "isList": false
                  }
                ]
              },
              {
                "name": "skip",
                "inputType": [
                  {
                    "type": "String",
                    "kind": "scalar",
                    "isRequired": false,
                    "isList": false
                  }
                ]
              },
              {
                "name": "after",
                "inputType": [
                  {
                    "type": "String",
                    "kind": "scalar",
                    "isRequired": false,
                    "isList": false
                  }
                ]
              },
              {
                "name": "before",
                "inputType": [
                  {
                    "type": "String",
                    "kind": "scalar",
                    "isRequired": false,
                    "isList": false
                  }
                ]
              },
              {
                "name": "first",
                "inputType": [
                  {
                    "type": "Int",
                    "kind": "scalar",
                    "isRequired": false,
                    "isList": false
                  }
                ]
              },
              {
                "name": "last",
                "inputType": [
                  {
                    "type": "Int",
                    "kind": "scalar",
                    "isRequired": false,
                    "isList": false
                  }
                ]
              }
            ],
            "outputType": {
              "type": "Post",
              "kind": "object",
              "isRequired": false,
              "isList": true
            }
          },
          {
            "name": "post",
            "args": [
              {
                "name": "where",
                "inputType": [
                  {
                    "type": "PostWhereUniqueInput",
                    "kind": "object",
                    "isRequired": true,
                    "isList": false
                  }
                ]
              }
            ],
            "outputType": {
              "type": "Post",
              "kind": "object",
              "isRequired": false,
              "isList": false
            }
          },
          {
            "name": "locations",
            "args": [
              {
                "name": "where",
                "inputType": [
                  {
                    "type": "LocationWhereInput",
                    "kind": "object",
                    "isRequired": false,
                    "isList": false
                  }
                ]
              },
              {
                "name": "orderBy",
                "inputType": [
                  {
                    "type": "LocationOrderByInput",
                    "kind": "enum",
                    "isRequired": false,
                    "isList": false
                  }
                ]
              },
              {
                "name": "skip",
                "inputType": [
                  {
                    "type": "String",
                    "kind": "scalar",
                    "isRequired": false,
                    "isList": false
                  }
                ]
              },
              {
                "name": "after",
                "inputType": [
                  {
                    "type": "String",
                    "kind": "scalar",
                    "isRequired": false,
                    "isList": false
                  }
                ]
              },
              {
                "name": "before",
                "inputType": [
                  {
                    "type": "String",
                    "kind": "scalar",
                    "isRequired": false,
                    "isList": false
                  }
                ]
              },
              {
                "name": "first",
                "inputType": [
                  {
                    "type": "Int",
                    "kind": "scalar",
                    "isRequired": false,
                    "isList": false
                  }
                ]
              },
              {
                "name": "last",
                "inputType": [
                  {
                    "type": "Int",
                    "kind": "scalar",
                    "isRequired": false,
                    "isList": false
                  }
                ]
              }
            ],
            "outputType": {
              "type": "Location",
              "kind": "object",
              "isRequired": false,
              "isList": true
            }
          },
          {
            "name": "location",
            "args": [
              {
                "name": "where",
                "inputType": [
                  {
                    "type": "LocationWhereUniqueInput",
                    "kind": "object",
                    "isRequired": true,
                    "isList": false
                  }
                ]
              }
            ],
            "outputType": {
              "type": "Location",
              "kind": "object",
              "isRequired": false,
              "isList": false
            }
          }
        ]
      },
      {
        "name": "Mutation",
        "fields": [
          {
            "name": "createUser",
            "args": [
              {
                "name": "data",
                "inputType": [
                  {
                    "type": "UserCreateInput",
                    "kind": "object",
                    "isRequired": true,
                    "isList": false
                  }
                ]
              }
            ],
            "outputType": {
              "type": "User",
              "kind": "object",
              "isRequired": true,
              "isList": false
            }
          },
          {
            "name": "createPost",
            "args": [
              {
                "name": "data",
                "inputType": [
                  {
                    "type": "PostCreateInput",
                    "kind": "object",
                    "isRequired": true,
                    "isList": false
                  }
                ]
              }
            ],
            "outputType": {
              "type": "Post",
              "kind": "object",
              "isRequired": true,
              "isList": false
            }
          },
          {
            "name": "createLocation",
            "args": [
              {
                "name": "data",
                "inputType": [
                  {
                    "type": "LocationCreateInput",
                    "kind": "object",
                    "isRequired": true,
                    "isList": false
                  }
                ]
              }
            ],
            "outputType": {
              "type": "Location",
              "kind": "object",
              "isRequired": true,
              "isList": false
            }
          }
        ]
      }
    ],
    "inputTypes": [
      {
        "name": "LocationWhereInput",
        "fields": [
          {
            "name": "id",
            "inputType": [
              {
                "isList": false,
                "isRequired": false,
                "kind": "scalar",
                "type": "Int"
              },
              {
                "type": "IntFilter",
                "isList": false,
                "isRequired": false,
                "kind": "object"
              }
            ],
            "isRelationFilter": false
          },
          {
            "name": "city",
            "inputType": [
              {
                "isList": false,
                "isRequired": false,
                "kind": "scalar",
                "type": "String"
              },
              {
                "type": "StringFilter",
                "isList": false,
                "isRequired": false,
                "kind": "object"
              }
            ],
            "isRelationFilter": false
          },
          {
            "name": "AND",
            "inputType": [
              {
                "type": "LocationWhereInput",
                "kind": "object",
                "isRequired": false,
                "isList": true
              }
            ],
            "isRelationFilter": true
          },
          {
            "name": "OR",
            "inputType": [
              {
                "type": "LocationWhereInput",
                "kind": "object",
                "isRequired": false,
                "isList": true
              }
            ],
            "isRelationFilter": true
          },
          {
            "name": "NOT",
            "inputType": [
              {
                "type": "LocationWhereInput",
                "kind": "object",
                "isRequired": false,
                "isList": true
              }
            ],
            "isRelationFilter": true
          },
          {
            "name": "user",
            "inputType": [
              {
                "type": "UserWhereInput",
                "kind": "object",
                "isRequired": false,
                "isList": false
              }
            ],
            "isRelationFilter": true
          }
        ],
        "isWhereType": true,
        "atLeastOne": true
      },
      {
        "name": "PostWhereInput",
        "fields": [
          {
            "name": "id",
            "inputType": [
              {
                "isList": false,
                "isRequired": false,
                "kind": "scalar",
                "type": "Int"
              },
              {
                "type": "IntFilter",
                "isList": false,
                "isRequired": false,
                "kind": "object"
              }
            ],
            "isRelationFilter": false
          },
          {
            "name": "name",
            "inputType": [
              {
                "isList": false,
                "isRequired": false,
                "kind": "scalar",
                "type": "String"
              },
              {
                "type": "StringFilter",
                "isList": false,
                "isRequired": false,
                "kind": "object"
              }
            ],
            "isRelationFilter": false
          },
          {
            "name": "email",
            "inputType": [
              {
                "isList": false,
                "isRequired": false,
                "kind": "scalar",
                "type": "String"
              },
              {
                "type": "StringFilter",
                "isList": false,
                "isRequired": false,
                "kind": "object"
              }
            ],
            "isRelationFilter": false
          },
          {
            "name": "AND",
            "inputType": [
              {
                "type": "PostWhereInput",
                "kind": "object",
                "isRequired": false,
                "isList": true
              }
            ],
            "isRelationFilter": true
          },
          {
            "name": "OR",
            "inputType": [
              {
                "type": "PostWhereInput",
                "kind": "object",
                "isRequired": false,
                "isList": true
              }
            ],
            "isRelationFilter": true
          },
          {
            "name": "NOT",
            "inputType": [
              {
                "type": "PostWhereInput",
                "kind": "object",
                "isRequired": false,
                "isList": true
              }
            ],
            "isRelationFilter": true
          },
          {
            "name": "user",
            "inputType": [
              {
                "type": "UserWhereInput",
                "kind": "object",
                "isRequired": false,
                "isList": false
              }
            ],
            "isRelationFilter": true
          }
        ],
        "isWhereType": true,
        "atLeastOne": true
      },
      {
        "name": "UserWhereInput",
        "fields": [
          {
            "name": "id",
            "inputType": [
              {
                "isList": false,
                "isRequired": false,
                "kind": "scalar",
                "type": "Int"
              },
              {
                "type": "IntFilter",
                "isList": false,
                "isRequired": false,
                "kind": "object"
              }
            ],
            "isRelationFilter": false
          },
          {
            "name": "name",
            "inputType": [
              {
                "isList": false,
                "isRequired": false,
                "kind": "scalar",
                "type": "String"
              },
              {
                "type": "StringFilter",
                "isList": false,
                "isRequired": false,
                "kind": "object"
              }
            ],
            "isRelationFilter": false
          },
          {
            "name": "email",
            "inputType": [
              {
                "isList": false,
                "isRequired": false,
                "kind": "scalar",
                "type": "String"
              },
              {
                "type": "StringFilter",
                "isList": false,
                "isRequired": false,
                "kind": "object"
              }
            ],
            "isRelationFilter": false
          },
          {
            "name": "status",
            "inputType": [
              {
                "isList": false,
                "isRequired": false,
                "kind": "scalar",
                "type": "String"
              },
              {
                "type": "StringFilter",
                "isList": false,
                "isRequired": false,
                "kind": "object"
              }
            ],
            "isRelationFilter": false
          },
          {
            "name": "favoriteTree",
            "inputType": [
              {
                "isList": false,
                "isRequired": false,
                "kind": "enum",
                "type": "Tree"
              },
              {
                "type": "TreeFilter",
                "isList": false,
                "isRequired": false,
                "kind": "object"
              }
            ],
            "isRelationFilter": false
          },
          {
            "name": "posts",
            "inputType": [
              {
                "type": "PostFilter",
                "isList": false,
                "isRequired": false,
                "kind": "object"
              }
            ],
            "isRelationFilter": false
          },
          {
            "name": "AND",
            "inputType": [
              {
                "type": "UserWhereInput",
                "kind": "object",
                "isRequired": false,
                "isList": true
              }
            ],
            "isRelationFilter": true
          },
          {
            "name": "OR",
            "inputType": [
              {
                "type": "UserWhereInput",
                "kind": "object",
                "isRequired": false,
                "isList": true
              }
            ],
            "isRelationFilter": true
          },
          {
            "name": "NOT",
            "inputType": [
              {
                "type": "UserWhereInput",
                "kind": "object",
                "isRequired": false,
                "isList": true
              }
            ],
            "isRelationFilter": true
          },
          {
            "name": "location",
            "inputType": [
              {
                "type": "LocationWhereInput",
                "kind": "object",
                "isRequired": false,
                "isList": false
              }
            ],
            "isRelationFilter": true
          }
        ],
        "isWhereType": true,
        "atLeastOne": true
      },
      {
        "name": "UserWhereUniqueInput",
        "fields": [
          {
            "name": "id",
            "inputType": [
              {
                "type": "Int",
                "kind": "scalar",
                "isRequired": false,
                "isList": false
              }
            ]
          },
          {
            "name": "email",
            "inputType": [
              {
                "type": "String",
                "kind": "scalar",
                "isRequired": false,
                "isList": false
              }
            ]
          }
        ]
      },
      {
        "name": "PostWhereUniqueInput",
        "fields": [
          {
            "name": "id",
            "inputType": [
              {
                "type": "Int",
                "kind": "scalar",
                "isRequired": false,
                "isList": false
              }
            ]
          },
          {
            "name": "email",
            "inputType": [
              {
                "type": "String",
                "kind": "scalar",
                "isRequired": false,
                "isList": false
              }
            ]
          }
        ]
      },
      {
        "name": "LocationWhereUniqueInput",
        "fields": [
          {
            "name": "id",
            "inputType": [
              {
                "type": "Int",
                "kind": "scalar",
                "isRequired": false,
                "isList": false
              }
            ]
          }
        ]
      },
      {
        "name": "UserCreatenicknamesInput",
        "fields": [
          {
            "name": "set",
            "inputType": [
              {
                "type": "String",
                "kind": "scalar",
                "isRequired": false,
                "isList": true
              }
            ]
          }
        ]
      },
      {
        "name": "UserCreatepermissionsInput",
        "fields": [
          {
            "name": "set",
            "inputType": [
              {
                "type": "Permission",
                "kind": "enum",
                "isRequired": false,
                "isList": true
              }
            ]
          }
        ]
      },
      {
        "name": "LocationCreateWithoutUserInput",
        "fields": [
          {
            "name": "city",
            "inputType": [
              {
                "type": "String",
                "kind": "scalar",
                "isRequired": true,
                "isList": false
              }
            ]
          }
        ]
      },
      {
        "name": "LocationCreateOneWithoutLocationInput",
        "fields": [
          {
            "name": "create",
            "inputType": [
              {
                "type": "LocationCreateWithoutUserInput",
                "kind": "object",
                "isRequired": false,
                "isList": false
              }
            ]
          },
          {
            "name": "connect",
            "inputType": [
              {
                "type": "LocationWhereUniqueInput",
                "kind": "object",
                "isRequired": false,
                "isList": false
              }
            ]
          }
        ]
      },
      {
        "name": "PostCreateWithoutUserInput",
        "fields": [
          {
            "name": "name",
            "inputType": [
              {
                "type": "String",
                "kind": "scalar",
                "isRequired": true,
                "isList": false
              }
            ]
          },
          {
            "name": "email",
            "inputType": [
              {
                "type": "String",
                "kind": "scalar",
                "isRequired": true,
                "isList": false
              }
            ]
          }
        ]
      },
      {
        "name": "PostCreateManyWithoutPostsInput",
        "fields": [
          {
            "name": "create",
            "inputType": [
              {
                "type": "PostCreateWithoutUserInput",
                "kind": "object",
                "isRequired": false,
                "isList": true
              }
            ]
          },
          {
            "name": "connect",
            "inputType": [
              {
                "type": "PostWhereUniqueInput",
                "kind": "object",
                "isRequired": false,
                "isList": true
              }
            ]
          }
        ]
      },
      {
        "name": "UserCreateInput",
        "fields": [
          {
            "name": "name",
            "inputType": [
              {
                "type": "String",
                "kind": "scalar",
                "isRequired": true,
                "isList": false
              }
            ]
          },
          {
            "name": "email",
            "inputType": [
              {
                "type": "String",
                "kind": "scalar",
                "isRequired": true,
                "isList": false
              }
            ]
          },
          {
            "name": "status",
            "inputType": [
              {
                "type": "String",
                "kind": "scalar",
                "isRequired": true,
                "isList": false
              }
            ]
          },
          {
            "name": "favoriteTree",
            "inputType": [
              {
                "type": "Tree",
                "kind": "enum",
                "isRequired": true,
                "isList": false
              }
            ]
          },
          {
            "name": "nicknames",
            "inputType": [
              {
                "type": "UserCreatenicknamesInput",
                "kind": "object",
                "isRequired": false,
                "isList": false
              }
            ]
          },
          {
            "name": "permissions",
            "inputType": [
              {
                "type": "UserCreatepermissionsInput",
                "kind": "object",
                "isRequired": false,
                "isList": false
              }
            ]
          },
          {
            "name": "location",
            "inputType": [
              {
                "type": "LocationCreateOneWithoutLocationInput",
                "kind": "object",
                "isRequired": true,
                "isList": false
              }
            ]
          },
          {
            "name": "posts",
            "inputType": [
              {
                "type": "PostCreateManyWithoutPostsInput",
                "kind": "object",
                "isRequired": false,
                "isList": false
              }
            ]
          }
        ]
      },
      {
        "name": "UserCreateWithoutPostsInput",
        "fields": [
          {
            "name": "name",
            "inputType": [
              {
                "type": "String",
                "kind": "scalar",
                "isRequired": true,
                "isList": false
              }
            ]
          },
          {
            "name": "email",
            "inputType": [
              {
                "type": "String",
                "kind": "scalar",
                "isRequired": true,
                "isList": false
              }
            ]
          },
          {
            "name": "status",
            "inputType": [
              {
                "type": "String",
                "kind": "scalar",
                "isRequired": true,
                "isList": false
              }
            ]
          },
          {
            "name": "favoriteTree",
            "inputType": [
              {
                "type": "Tree",
                "kind": "enum",
                "isRequired": true,
                "isList": false
              }
            ]
          },
          {
            "name": "nicknames",
            "inputType": [
              {
                "type": "UserCreatenicknamesInput",
                "kind": "object",
                "isRequired": false,
                "isList": false
              }
            ]
          },
          {
            "name": "permissions",
            "inputType": [
              {
                "type": "UserCreatepermissionsInput",
                "kind": "object",
                "isRequired": false,
                "isList": false
              }
            ]
          },
          {
            "name": "location",
            "inputType": [
              {
                "type": "LocationCreateOneWithoutLocationInput",
                "kind": "object",
                "isRequired": true,
                "isList": false
              }
            ]
          }
        ]
      },
      {
        "name": "UserCreateOneWithoutUserInput",
        "fields": [
          {
            "name": "create",
            "inputType": [
              {
                "type": "UserCreateWithoutPostsInput",
                "kind": "object",
                "isRequired": false,
                "isList": false
              }
            ]
          },
          {
            "name": "connect",
            "inputType": [
              {
                "type": "UserWhereUniqueInput",
                "kind": "object",
                "isRequired": false,
                "isList": false
              }
            ]
          }
        ]
      },
      {
        "name": "PostCreateInput",
        "fields": [
          {
            "name": "name",
            "inputType": [
              {
                "type": "String",
                "kind": "scalar",
                "isRequired": true,
                "isList": false
              }
            ]
          },
          {
            "name": "email",
            "inputType": [
              {
                "type": "String",
                "kind": "scalar",
                "isRequired": true,
                "isList": false
              }
            ]
          },
          {
            "name": "user",
            "inputType": [
              {
                "type": "UserCreateOneWithoutUserInput",
                "kind": "object",
                "isRequired": false,
                "isList": false
              }
            ]
          }
        ]
      },
      {
        "name": "LocationCreateInput",
        "fields": [
          {
            "name": "city",
            "inputType": [
              {
                "type": "String",
                "kind": "scalar",
                "isRequired": true,
                "isList": false
              }
            ]
          },
          {
            "name": "user",
            "inputType": [
              {
                "type": "UserCreateOneWithoutUserInput",
                "kind": "object",
                "isRequired": false,
                "isList": false
              }
            ]
          }
        ]
      },
      {
        "name": "IntFilter",
        "fields": [
          {
            "name": "equals",
            "inputType": [
              {
                "isList": false,
                "isRequired": false,
                "kind": "scalar",
                "type": "Int"
              }
            ]
          },
          {
            "name": "not",
            "inputType": [
              {
                "isList": false,
                "isRequired": false,
                "kind": "scalar",
                "type": "Int"
              },
              {
                "isList": false,
                "isRequired": false,
                "kind": "scalar",
                "type": "IntFilter"
              }
            ]
          },
          {
            "name": "in",
            "inputType": [
              {
                "isList": true,
                "isRequired": false,
                "kind": "scalar",
                "type": "Int"
              }
            ]
          },
          {
            "name": "notIn",
            "inputType": [
              {
                "isList": true,
                "isRequired": false,
                "kind": "scalar",
                "type": "Int"
              }
            ]
          },
          {
            "name": "lt",
            "inputType": [
              {
                "isList": false,
                "isRequired": false,
                "kind": "scalar",
                "type": "Int"
              }
            ]
          },
          {
            "name": "lte",
            "inputType": [
              {
                "isList": false,
                "isRequired": false,
                "kind": "scalar",
                "type": "Int"
              }
            ]
          },
          {
            "name": "gt",
            "inputType": [
              {
                "isList": false,
                "isRequired": false,
                "kind": "scalar",
                "type": "Int"
              }
            ]
          },
          {
            "name": "gte",
            "inputType": [
              {
                "isList": false,
                "isRequired": false,
                "kind": "scalar",
                "type": "Int"
              }
            ]
          }
        ],
        "atLeastOne": true
      },
      {
        "name": "StringFilter",
        "fields": [
          {
            "name": "equals",
            "inputType": [
              {
                "isList": false,
                "isRequired": false,
                "kind": "scalar",
                "type": "String"
              }
            ]
          },
          {
            "name": "not",
            "inputType": [
              {
                "isList": false,
                "isRequired": false,
                "kind": "scalar",
                "type": "String"
              },
              {
                "isList": false,
                "isRequired": false,
                "kind": "scalar",
                "type": "StringFilter"
              }
            ]
          },
          {
            "name": "in",
            "inputType": [
              {
                "isList": true,
                "isRequired": false,
                "kind": "scalar",
                "type": "String"
              }
            ]
          },
          {
            "name": "notIn",
            "inputType": [
              {
                "isList": true,
                "isRequired": false,
                "kind": "scalar",
                "type": "String"
              }
            ]
          },
          {
            "name": "lt",
            "inputType": [
              {
                "isList": false,
                "isRequired": false,
                "kind": "scalar",
                "type": "String"
              }
            ]
          },
          {
            "name": "lte",
            "inputType": [
              {
                "isList": false,
                "isRequired": false,
                "kind": "scalar",
                "type": "String"
              }
            ]
          },
          {
            "name": "gt",
            "inputType": [
              {
                "isList": false,
                "isRequired": false,
                "kind": "scalar",
                "type": "String"
              }
            ]
          },
          {
            "name": "gte",
            "inputType": [
              {
                "isList": false,
                "isRequired": false,
                "kind": "scalar",
                "type": "String"
              }
            ]
          },
          {
            "name": "contains",
            "inputType": [
              {
                "isList": false,
                "isRequired": false,
                "kind": "scalar",
                "type": "String"
              }
            ]
          },
          {
            "name": "startsWith",
            "inputType": [
              {
                "isList": false,
                "isRequired": false,
                "kind": "scalar",
                "type": "String"
              }
            ]
          },
          {
            "name": "endsWith",
            "inputType": [
              {
                "isList": false,
                "isRequired": false,
                "kind": "scalar",
                "type": "String"
              }
            ]
          }
        ],
        "atLeastOne": true
      },
      {
        "name": "TreeFilter",
        "fields": [],
        "atLeastOne": true
      },
      {
        "name": "PostFilter",
        "fields": [
          {
            "name": "every",
            "inputType": [
              {
                "isList": false,
                "isRequired": false,
                "kind": "scalar",
                "type": "PostWhereInput"
              }
            ]
          },
          {
            "name": "some",
            "inputType": [
              {
                "isList": false,
                "isRequired": false,
                "kind": "scalar",
                "type": "PostWhereInput"
              }
            ]
          },
          {
            "name": "none",
            "inputType": [
              {
                "isList": false,
                "isRequired": false,
                "kind": "scalar",
                "type": "PostWhereInput"
              }
            ]
          }
        ],
        "atLeastOne": true
      },
      {
        "name": "UserOrderByInput",
        "atLeastOne": true,
        "atMostOne": true,
        "isOrderType": true,
        "fields": [
          {
            "name": "id",
            "inputType": [
              {
                "type": "OrderByArg",
                "isList": false,
                "isRequired": false,
                "kind": "scalar"
              }
            ],
            "isRelationFilter": false
          },
          {
            "name": "name",
            "inputType": [
              {
                "type": "OrderByArg",
                "isList": false,
                "isRequired": false,
                "kind": "scalar"
              }
            ],
            "isRelationFilter": false
          },
          {
            "name": "email",
            "inputType": [
              {
                "type": "OrderByArg",
                "isList": false,
                "isRequired": false,
                "kind": "scalar"
              }
            ],
            "isRelationFilter": false
          },
          {
            "name": "status",
            "inputType": [
              {
                "type": "OrderByArg",
                "isList": false,
                "isRequired": false,
                "kind": "scalar"
              }
            ],
            "isRelationFilter": false
          },
          {
            "name": "favoriteTree",
            "inputType": [
              {
                "type": "OrderByArg",
                "isList": false,
                "isRequired": false,
                "kind": "scalar"
              }
            ],
            "isRelationFilter": false
          }
        ]
      },
      {
        "name": "PostOrderByInput",
        "atLeastOne": true,
        "atMostOne": true,
        "isOrderType": true,
        "fields": [
          {
            "name": "id",
            "inputType": [
              {
                "type": "OrderByArg",
                "isList": false,
                "isRequired": false,
                "kind": "scalar"
              }
            ],
            "isRelationFilter": false
          },
          {
            "name": "name",
            "inputType": [
              {
                "type": "OrderByArg",
                "isList": false,
                "isRequired": false,
                "kind": "scalar"
              }
            ],
            "isRelationFilter": false
          },
          {
            "name": "email",
            "inputType": [
              {
                "type": "OrderByArg",
                "isList": false,
                "isRequired": false,
                "kind": "scalar"
              }
            ],
            "isRelationFilter": false
          }
        ]
      },
      {
        "name": "LocationOrderByInput",
        "atLeastOne": true,
        "atMostOne": true,
        "isOrderType": true,
        "fields": [
          {
            "name": "id",
            "inputType": [
              {
                "type": "OrderByArg",
                "isList": false,
                "isRequired": false,
                "kind": "scalar"
              }
            ],
            "isRelationFilter": false
          },
          {
            "name": "city",
            "inputType": [
              {
                "type": "OrderByArg",
                "isList": false,
                "isRequired": false,
                "kind": "scalar"
              }
            ],
            "isRelationFilter": false
          }
        ]
      }
    ]
  }
}